<?xml version="1.0" encoding="ISO-8859-1" ?>
<!DOCTYPE tiles-definitions PUBLIC
		"-//Apache Software Foundation//DTD Tiles Configuration 2.1//EN"
		"http://tiles.apache.org/dtds/tiles-config_2_1.dtd">

<tiles-definitions>
	<definition name="knowledgeBase" extends="pageTemplate">
		<put-attribute name="content" value="/WEB-INF/jsp/knowledgeBase/knowledgeBaseHome.jsp" />
	</definition>
	<definition name="approvals" extends="pageTemplate">
		<put-attribute name="content" value="/WEB-INF/jsp/approvals/approvalsHome.jsp" />
	</definition>
	<definition name="tasks" extends="pageTemplate">
		<put-attribute name="content" value="/WEB-INF/jsp/tasks/tasksHome.jsp" />
	</definition>
	<definition name="surveys" extends="pageTemplate">
		<put-attribute name="content" value="/WEB-INF/jsp/surveys/surveysHome.jsp" />
	</definition>
	<definition name="reporting" extends="pageTemplate">
		<put-attribute name="content" value="/WEB-INF/jsp/reporting/reportingHome.jsp" />
	</definition>
</tiles-definitions>
